MANIFEST.in
README.md
setup.py
return_type/__init__.py
return_type/mypy-plugin.py
return_type/py.typed
return_type/return_type.py
return_type.egg-info/PKG-INFO
return_type.egg-info/SOURCES.txt
return_type.egg-info/dependency_links.txt
return_type.egg-info/requires.txt
return_type.egg-info/top_level.txt