Metadata-Version: 2.1
Name: return-type
Version: 0.1.1
Summary: Generic type ReturnType and mypy checker plugin
Home-page: https://github.com/wlf100220/return_type
Author: Dimitri.WEI
Author-email: dimitri.wei.lingfeng@gmail.com
License: UNKNOWN
Platform: UNKNOWN
Requires-Python: >=3.8
